odoo10_addon_website_snippet_data_slider-10.0.1.0.0-py2.7-nspkg.pth
odoo10_addon_website_snippet_data_slider-10.0.1.0.0.dist-info/top_level.txt
odoo10_addon_website_snippet_data_slider-10.0.1.0.0.dist-info/WHEEL
odoo10_addon_website_snippet_data_slider-10.0.1.0.0.dist-info/RECORD
odoo10_addon_website_snippet_data_slider-10.0.1.0.0.dist-info/metadata.json
odoo10_addon_website_snippet_data_slider-10.0.1.0.0.dist-info/DESCRIPTION.rst
odoo10_addon_website_snippet_data_slider-10.0.1.0.0.dist-info/METADATA
odoo10_addon_website_snippet_data_slider-10.0.1.0.0.dist-info/namespace_packages.txt
odoo/addons/website_snippet_data_slider/__manifest__.py
odoo/addons/website_snippet_data_slider/__init__.py
odoo/addons/website_snippet_data_slider/README.rst
odoo/addons/website_snippet_data_slider/views/snippet_template.xml
odoo/addons/website_snippet_data_slider/views/assets.xml
odoo/addons/website_snippet_data_slider/controllers/main.py
odoo/addons/website_snippet_data_slider/controllers/__init__.py
odoo/addons/website_snippet_data_slider/demo/data_slider_demo.xml
odoo/addons/website_snippet_data_slider/static/description/screenshot.png
odoo/addons/website_snippet_data_slider/static/description/widget_icon.png
odoo/addons/website_snippet_data_slider/static/description/icon.png
odoo/addons/website_snippet_data_slider/static/lib/slick-1.6.0/slick-theme.css
odoo/addons/website_snippet_data_slider/static/lib/slick-1.6.0/slick-theme.less
odoo/addons/website_snippet_data_slider/static/lib/slick-1.6.0/slick.js
odoo/addons/website_snippet_data_slider/static/lib/slick-1.6.0/ajax-loader.gif
odoo/addons/website_snippet_data_slider/static/lib/slick-1.6.0/config.rb
odoo/addons/website_snippet_data_slider/static/lib/slick-1.6.0/slick.scss
odoo/addons/website_snippet_data_slider/static/lib/slick-1.6.0/slick.css
odoo/addons/website_snippet_data_slider/static/lib/slick-1.6.0/slick-theme.scss
odoo/addons/website_snippet_data_slider/static/lib/slick-1.6.0/slick.min.js
odoo/addons/website_snippet_data_slider/static/lib/slick-1.6.0/slick.less
odoo/addons/website_snippet_data_slider/static/lib/slick-1.6.0/fonts/slick.ttf
odoo/addons/website_snippet_data_slider/static/lib/slick-1.6.0/fonts/slick.svg
odoo/addons/website_snippet_data_slider/static/lib/slick-1.6.0/fonts/slick.woff
odoo/addons/website_snippet_data_slider/static/lib/slick-1.6.0/fonts/slick.eot
odoo/addons/website_snippet_data_slider/static/src/js/data_slider.editor.js
