Metadata-Version: 2.0
Name: odoo10-addon-website-snippet-data-slider
Version: 10.0.1.0.0
Summary: Abstract data slider for use on website.  Primary use (and default implementation) is product slider.
Home-page: https://laslabs.com/
Author: LasLabs, Odoo Community Association (OCA)
Author-email: support@odoo-community.org
License: LGPL-3
Platform: UNKNOWN
Requires-Dist: odoo (<10.1dev,>=10.0)
Classifier: Programming Language :: Python :: 2.7
Classifier: Framework :: Odoo
Classifier: License :: OSI Approved :: GNU Lesser General Public License v3 (LGPLv3)
